sop/__init__.py
sop/__main__.py
sop/__version__.py
sop/py.typed
sop-0.5.1.dist-info/LICENSE
sop-0.5.1.dist-info/METADATA
sop-0.5.1.dist-info/WHEEL
sop-0.5.1.dist-info/top_level.txt
sop-0.5.1.dist-info/RECORD
