Metadata-Version: 2.1
Name: sop
Version: 0.5.1
Summary: A framework for implementing the Stateless OpenPGP CLI
Home-page: https://gitlab.com/dkg/python-sop
Author: Daniel Kahn Gillmor
Author-email: dkg@fifthhorseman.net
Classifier: Development Status :: 3 - Alpha
Classifier: Environment :: Console
Classifier: Programming Language :: Python :: 3
Classifier: License :: OSI Approved :: MIT License
Classifier: Operating System :: OS Independent
Classifier: Topic :: Security
Classifier: Topic :: Security :: Cryptography
Requires-Python: >=3.7
License-File: LICENSE
